Metadata-Version: 2.1
Name: langchain-postgres
Version: 0.0.14
Summary: An integration package connecting Postgres and LangChain
Home-page: https://github.com/langchain-ai/langchain-postgres
License: MIT
Requires-Python: >=3.9,<4.0
Classifier: License :: OSI Approved :: MIT License
Classifier: Programming Language :: Python :: 3
Classifier: Programming Language :: Python :: 3.9
Classifier: Programming Language :: Python :: 3.10
Classifier: Programming Language :: Python :: 3.11
Classifier: Programming Language :: Python :: 3.12
Requires-Dist: asyncpg (>=0.30.0,<0.31.0)
Requires-Dist: langchain-core (>=0.2.13,<0.4.0)
Requires-Dist: numpy (>=1.21,<2.0)
Requires-Dist: pgvector (>=0.2.5,<0.4)
Requires-Dist: psycopg (>=3,<4)
Requires-Dist: psycopg-pool (>=3.2.1,<4.0.0)
Requires-Dist: sqlalchemy (>=2,<3)
Project-URL: Repository, https://github.com/langchain-ai/langchain-postgres
Project-URL: Source Code, https://github.com/langchain-ai/langchain-postgres/tree/master/langchain_postgres
